pypipy/__init__.py
pypipy/calculator.py
pypipy-0.0.4.2.dist-info/LICENSE
pypipy-0.0.4.2.dist-info/METADATA
pypipy-0.0.4.2.dist-info/WHEEL
pypipy-0.0.4.2.dist-info/top_level.txt
pypipy-0.0.4.2.dist-info/RECORD
