Metadata-Version: 2.1
Name: pypipy
Version: 0.0.4.2
Summary: oss-dev my pypi 0.0.4.2
Home-page: https://github.com/BOJ-ios/pypipy
Download-URL: https://github.com/BOJ-ios/pypipy/archive/refs/tags/v0.0.4.zip
Author: mingyukim
Author-email: 843850@donga.ac.kr
Classifier: Programming Language :: Python :: 3.11
Classifier: Operating System :: OS Independent
License-File: LICENSE
Requires-Dist: pytest
